result_collector_client/__init__.py
result_collector_client/collector.py
result_collector_client/models.py
result_collector_client/submitter.py
edustats_collector-0.2.0.dist-info/WHEEL
edustats_collector-0.2.0.dist-info/METADATA
edustats_collector-0.2.0.dist-info/RECORD
