Metadata-Version: 2.1
Name: edustats-collector
Version: 0.2.0
Summary: edustats collector client
Author: Nicola Jordan
Author-email: njordan.hsr@gmail.com
Requires-Python: >=3.10,<4.0
Classifier: Programming Language :: Python :: 3
Classifier: Programming Language :: Python :: 3.10
Requires-Dist: pydantic (>=1.9.0,<2.0.0)
Requires-Dist: requests (>=2.27.1,<3.0.0)
